{"session_id":"fi-session:2026-07-17t000530-0400","timestamp":"2026-07-17T00:05:30-04:00","parent_session":"fi-session:2026-07-16t230519-0400","active_projects":["fi-project:foundation-intelligence","fi-project:mirror-cartographer"],"referenced_artifacts":["fi-artifact:project-graph-v1"],"decisions_made":[],"evidence_added":["fi-evidence:project-graph-missing-before-bootstrap-20260717"],"unresolved_questions":["Initialize the remaining required graph and index files."],"privacy_classification":"internal","next_handoff":{"verification_step":"Initialize decision-log.jsonl.","trigger_dedupe_key":"fi-trigger:initialize-decision-log:v1"}}