{
  "schema_version": "1.0.0",
  "queue_item": "W-001",
  "owner": "independent_creative_web",
  "recorded_at": "2026-07-12T04:24:00Z",
  "status": "implemented_source_unverified_deployment",
  "completed_slice": "Created Afterimage Orchard, a self-contained generative artwork with pointer-grown light organisms, transient weather, and optional gesture-activated sound.",
  "specialists_used": [
    "Creative Director",
    "Worldbuilder",
    "Experimental Interface Designer",
    "Generative Media Engineer",
    "Independent Hosting Architect"
  ],
  "artifacts": [
    "independent-web/afterimage-orchard/index.html",
    "independent-web/afterimage-orchard/IDENTITY.md",
    "operations/evidence/independent-web-afterimage-orchard-2026-07-12T0424Z.json"
  ],
  "commits": [
    "09829e2bb4f8b72a261310ab27d026af6433b3e0",
    "85fa235b56b533d3830675533b625c3b7d590c34",
    "3d400c23ba6426e672ca61afc3240c637b6b9f9f"
  ],
  "required_evidence": {
    "site_source": "satisfied",
    "distinct_identity_statement": "satisfied",
    "public_url": "unresolved",
    "mobile_proof": "unresolved"
  },
  "next_action": "Attach this directory to an independent static host, record immutable deployment identity, then capture desktop and narrow-viewport interaction evidence without changing its creative premise."
}